cs/mediainfo.py
cs.mediainfo-20240519.dist-info/METADATA
cs.mediainfo-20240519.dist-info/WHEEL
cs.mediainfo-20240519.dist-info/top_level.txt
cs.mediainfo-20240519.dist-info/RECORD
