Metadata-Version: 2.1
Name: cs.mediainfo
Version: 20240519
Summary: Simple minded facilities for media information. This contains mostly lexical functions for extracting information from strings or constructing media filenames from metadata.
Author-email: Cameron Simpson <cs@cskk.id.au>
License: GNU General Public License v3 or later (GPLv3+)
Project-URL: URL, https://bitbucket.org/cameron_simpson/css/commits/all
Keywords: python2,python3
Platform: UNKNOWN
Classifier: Programming Language :: Python
Classifier: Programming Language :: Python :: 3
Classifier: Development Status :: 4 - Beta
Classifier: Intended Audience :: Developers
Classifier: Operating System :: OS Independent
Classifier: Topic :: Software Development :: Libraries :: Python Modules
Classifier: License :: OSI Approved :: GNU General Public License v3 or later (GPLv3+)
Requires-Dist: cs.deco >=20240412
Requires-Dist: cs.gimmicks >=20240316
Requires-Dist: cs.lex >=20240519
Requires-Dist: cs.pfx >=20240412
Requires-Dist: cs.tagset >=20240422.2
